{
  "$schema": "https://developer.microsoft.com/json-schemas/spfx-build/package-solution.schema.json",
  "solution": {
    "name": "command-set-client-side-solution",
    "id": "1d4ec2b8-9af2-46f5-a344-047b07ae2005",
    "version": "1.0.0.0",
    "includeClientSideAssets": true,
    "isDomainIsolated": false,
    "features": [
      {
        "title": "Application Extension - Deployment of custom action.",
        "description": "Deploys a custom action with ClientSideComponentId association",
        "id": "d3312fbc-6248-4a2b-a246-8bd9f8b9d84f",
        "version": "1.0.0.0",
        "assets": {
          "elementManifests": [
            "elements.xml",
            "clientsideinstance.xml"
          ]
        }
      }
    ]
  },
  "paths": {
    "zippedPackage": "solution/command-set.sppkg"
  }
}
